sparta_airflow_timetables/__init__.py
sparta_airflow_timetables/anbima_holidays.csv
sparta_airflow_timetables/b3pregao_holidays.csv
sparta_airflow_timetables/timetables.py
sparta_airflow_timetables-1.0.1.dist-info/LICENSE
sparta_airflow_timetables-1.0.1.dist-info/METADATA
sparta_airflow_timetables-1.0.1.dist-info/WHEEL
sparta_airflow_timetables-1.0.1.dist-info/top_level.txt
sparta_airflow_timetables-1.0.1.dist-info/RECORD
